{
  "title": "Ortho Clínica",
  "order_info": "Información del Pedido",
  "shipping_info": "Información de Envío",
  "order_total": "Total del Pedido",
  "order_number": "Número de Pedido",
  "purchase_order": "Orden de Compra",
  "order_status": "Estado del Pedido",
  "order_type": "Tipo de Pedido",
  "company": "Empresa",
  "location": "Ubicación",
  "country": "País",
  "via": "A-través-de",
  "order_value": "Valor del Pedido",
  "taxes": "Impuestos",
  "shipping_and_handling": "Envío y Manejo",
  "order_total_amount": "Total del Pedido",
  "item": "Artículo",
  "material_number": "Número de Material",
  "description": "Descripción",
  "est_del_date": "Fecha Estimada de Entrega",
  "order_quantity": "Cantidad de Pedido",
  "UOM": "Unidad de Medida",
  "back_quantity": "Cantidad Atrasada",
  "cancel_quantity": "Cantidad Cancelada",
  "ship_quantity": "Cantidad Enviada",
  "status": "Estado"
}
